nsbl/__init__.py
nsbl/defaults.py
nsbl/exceptions.py
nsbl/frkl.info
nsbl/inventory.py
nsbl/nsbl.py
nsbl/nsbl_callback.py
nsbl/nsbl_tasklist.py
nsbl/role_utils.py
nsbl/runner.py
nsbl/tasklist_utils.py
nsbl/external/mitogen/mitogen-0.2.9.tar.gz
nsbl/external/nsbl-environment-template/README.md
nsbl/external/nsbl-environment-template/cookiecutter.json
nsbl/external/nsbl-environment-template/{{cookiecutter.env_dir}}/LICENSE
nsbl/external/nsbl-environment-template/{{cookiecutter.env_dir}}/README.md
nsbl/external/nsbl-environment-template/{{cookiecutter.env_dir}}/create-vault.sh
nsbl/external/nsbl-environment-template/{{cookiecutter.env_dir}}/run_all_plays.sh
nsbl/external/nsbl-environment-template/{{cookiecutter.env_dir}}/debug/ansible.cfg
nsbl/external/nsbl-environment-template/{{cookiecutter.env_dir}}/debug/debug_all_plays.sh
nsbl/external/nsbl-environment-template/{{cookiecutter.env_dir}}/logs/.readme.txt
nsbl/external/nsbl-environment-template/{{cookiecutter.env_dir}}/plays/ansible.cfg
nsbl/external/nsbl-environment-template/{{cookiecutter.env_dir}}/plays/init_plays.yml
nsbl/external/nsbl-environment-template/{{cookiecutter.env_dir}}/roles/external/roles_requirements.yml
nsbl/templates/external_role.yml
nsbl/templates/hosts
nsbl/templates/play.yml
nsbl-1.0.0.dist-info/AUTHORS.rst
nsbl-1.0.0.dist-info/LICENSE
nsbl-1.0.0.dist-info/METADATA
nsbl-1.0.0.dist-info/WHEEL
nsbl-1.0.0.dist-info/top_level.txt
nsbl-1.0.0.dist-info/RECORD
